Workbook

Sheet Summary
E2: Interpret the Results
B3: DDM | E3: Current Market Price: 564.15 INR (as of today’s close on 08Jan26). | Q3: Horizon | R3: Beta (β) | S3: R² | T3: Intercept | U3: Observations
B4: =DDM!B14 -> Label | C4: =DDM!C14 -> Value | E4: DDM Valuation: Base case (g = 0%, ke 24.93%) gives 1.00 INR, even optimistic scenarios (g = 4%, ke = 20%) only reach 1.563 INR. | Q4: 3 Years | R4: 2.87 | S4: 0.1471 | T4: −0.07098 | U4: 36
B5: =DDM!B15 -> Latest Dividend (D₀) | C5: =DDM!C15 -> 0.25 | Q5: 5 Years | R5: 2.77 | S5: 0.1707 | T5: −0.01405 | U5: 59
B6: =DDM!B16 -> Growth Rate (g) | C6: =DDM!C16 -> 0 | E6: Observation:
B7: =DDM!B17 -> Next Dividend (D₁) | C7: =DDM!C17 -> 0.25 | E7: DDM valuation is far below the market price because Adani Total Gas pays negligible dividends (0.25 INR annually).
B8: =DDM!B18 -> Required Return (kₑ) | C8: =DDM!C18 -> 0.2493422 | E8: DDM assumes value comes only from dividends, so it undervalues high-growth, low-dividend stocks.
B9: =DDM!B19 -> DDM Valuation: Price (P₀) | C9: =DDM!C19 -> 1.0026381 | E9: Market price reflects growth expectations and retained earnings, which DDM ignores.
B12: CAPM | E12: =CAPM!I20 -> Regression Statistics
B13: =CAPM!C65 -> Monthly Rm (avg) | C13: =CAPM!E65 -> 0.011024713 | E13: =CAPM!I21 -> Multiple R | F13: =CAPM!J21 -> 0.41321227
B14: =CAPM!C65 -> Monthly Rm (avg) | C14: =CAPM!E65 -> 0.011024713 | E14: =CAPM!I22 -> R Square | F14: =CAPM!J22 -> 0.17074438
B15: =CAPM!C66 -> Annual Rm | C15: =CAPM!E66 -> 0.13229656 | E15: =CAPM!I23 -> Adjusted R Square | F15: =CAPM!J23 -> 0.15619604
B16: =CAPM!C67 -> Monthly Rf | C16: =CAPM!E67 -> 0.0055191667 | E16: =CAPM!I24 -> Standard Error | F16: =CAPM!J24 -> 0.21858626
B17: =CAPM!C68 -> Annual Rf | C17: =CAPM!E68 -> 0.06623 | E17: =CAPM!I25 -> Observations | F17: =CAPM!J25 -> 59
B18: =CAPM!C69 -> Beta | C18: =CAPM!E69 -> 2.7716321
B19: =CAPM!C70 -> ke (annual CAPM) | C19: =CAPM!E70 -> 0.2493422
B23: ='Adani Total Gas Stock Price His'!A3 -> Date | C23: ='Adani Total Gas Stock Price His'!B3 -> Price | D23: ='Adani Total Gas Stock Price His'!J3 -> Volume (Million) | E23: Year | F23: Price (Ave) | G23: Volume M (Ave) | I23: =CAPM!C1 -> Rm = Ln return | J23: =CAPM!D1 -> ATGL (Ri) | K23: =CAPM!E1 -> Rf =10yrs govt bond = 6.623% pa | L23: Stock excess return = Ri − Rf | M23: Market excess return = Rm − Rf
B24: ='Adani Total Gas Stock Price His'!A4 -> 45669 | C24: ='Adani Total Gas Stock Price His'!B4 -> 566.7 | D24: ='Adani Total Gas Stock Price His'!J4 -> 8510000 | E24: =AVERAGE(B24:B35) -> 45663.5 | F24: =AVERAGE(C24:C35) -> 615.66667 | G24: =AVERAGE(D24:D35) -> 27959167 | I24: =CAPM!C2 -> -0.0028032285 | J24: =CAPM!D2 -> -0.068121955 | K24: =CAPM!E2 -> 0.0055191667 | L24: =(J24-K24) -> -0.073641122 | M24: =(I24-K24) -> -0.0083223952
B25: ='Adani Total Gas Stock Price His'!A5 -> 45668 | C25: ='Adani Total Gas Stock Price His'!B5 -> 606.65 | D25: ='Adani Total Gas Stock Price His'!J5 -> 9690000 | E25: =AVERAGE(B36:B47) -> 45297.5 | F25: =AVERAGE(C36:C47) -> 886.09167 | G25: =AVERAGE(D36:D47) -> 49972500 | I25: =CAPM!C3 -> 0.018521455 | J25: =CAPM!D3 -> -0.040304264 | K25: =CAPM!E3 -> 0.0055191667 | L25: =(J25-K25) -> -0.045823431 | M25: =(I25-K25) -> 0.013002289
B26: ='Adani Total Gas Stock Price His'!A6 -> 45667 | C26: ='Adani Total Gas Stock Price His'!B6 -> 631.6 | D26: ='Adani Total Gas Stock Price His'!J6 -> 25150000 | E26: =AVERAGE(B48:B59) -> 44932.5 | F26: =AVERAGE(C48:C59) -> 841.00417 | G26: =AVERAGE(D48:D59) -> 39465833 | I26: =CAPM!C4 -> 0.044152984 | J26: =CAPM!D4 -> 0.010024748 | K26: =CAPM!E4 -> 0.0055191667 | L26: =(J26-K26) -> 0.0045055811 | M26: =(I26-K26) -> 0.038633817
B27: ='Adani Total Gas Stock Price His'!A7 -> 45666 | C27: ='Adani Total Gas Stock Price His'!B7 -> 625.3 | D27: ='Adani Total Gas Stock Price His'!J7 -> 97480000 | E27: =AVERAGE(B60:B71) -> 44567.5 | F27: =AVERAGE(C60:C71) -> 2828.4792 | G27: =AVERAGE(D60:D71) -> 7441666.7 | I27: =CAPM!C5 -> 0.0075146236 | J27: =CAPM!D5 -> 0.056246327 | K27: =CAPM!E5 -> 0.0055191667 | L27: =(J27-K27) -> 0.05072716 | M27: =(I27-K27) -> 0.0019954569
B28: ='Adani Total Gas Stock Price His'!A8 -> 45665 | C28: ='Adani Total Gas Stock Price His'!B8 -> 591.1 | D28: ='Adani Total Gas Stock Price His'!J8 -> 13650000 | E28: =AVERAGE(B72:B83) -> 44202.5 | F28: =AVERAGE(C72:C83) -> 1158.6042 | G28: =AVERAGE(D72:D83) -> 26290000 | I28: =CAPM!C6 -> -0.013883691 | J28: =CAPM!D6 -> -0.021754539 | K28: =CAPM!E6 -> 0.0055191667 | L28: =(J28-K28) -> -0.027273706 | M28: =(I28-K28) -> -0.019402858
B29: ='Adani Total Gas Stock Price His'!A9 -> 45664 | C29: ='Adani Total Gas Stock Price His'!B9 -> 604.1 | D29: ='Adani Total Gas Stock Price His'!J9 -> 12980000 | I29: =CAPM!C7 -> -0.029780228 | J29: =CAPM!D7 -> -0.11208344 | K29: =CAPM!E7 -> 0.0055191667 | L29: =(J29-K29) -> -0.1176026 | M29: =(I29-K29) -> -0.035299394
B30: ='Adani Total Gas Stock Price His'!A10 -> 45663 | C30: ='Adani Total Gas Stock Price His'!B10 -> 675.75 | D30: ='Adani Total Gas Stock Price His'!J10 -> 38140000 | I30: =CAPM!C8 -> 0.030493085 | J30: =CAPM!D8 -> -0.011769169 | K30: =CAPM!E8 -> 0.0055191667 | L30: =(J30-K30) -> -0.017288335 | M30: =(I30-K30) -> 0.024973918
B31: ='Adani Total Gas Stock Price His'!A11 -> 45662 | C31: ='Adani Total Gas Stock Price His'!B11 -> 683.75 | D31: ='Adani Total Gas Stock Price His'!J11 -> 40220000 | I31: =CAPM!C9 -> 0.016971003 | J31: =CAPM!D9 -> 0.13032942 | K31: =CAPM!E9 -> 0.0055191667 | L31: =(J31-K31) -> 0.12481025 | M31: =(I31-K31) -> 0.011451836
B32: ='Adani Total Gas Stock Price His'!A12 -> 45661 | C32: ='Adani Total Gas Stock Price His'!B12 -> 600.2 | D32: ='Adani Total Gas Stock Price His'!J12 -> 15130000 | I32: =CAPM!C10 -> 0.034059282 | J32: =CAPM!D10 -> -0.0039906937 | K32: =CAPM!E10 -> 0.0055191667 | L32: =(J32-K32) -> -0.0095098604 | M32: =(I32-K32) -> 0.028540115
B33: ='Adani Total Gas Stock Price His'!A13 -> 45660 | C33: ='Adani Total Gas Stock Price His'!B13 -> 602.6 | D33: ='Adani Total Gas Stock Price His'!J13 -> 25540000 | I33: =CAPM!C11 -> 0.061128855 | J33: =CAPM!D11 -> 0.078419123 | K33: =CAPM!E11 -> 0.0055191667 | L33: =(J33-K33) -> 0.072899957 | M33: =(I33-K33) -> 0.055609688
B34: ='Adani Total Gas Stock Price His'!A14 -> 45659 | C34: ='Adani Total Gas Stock Price His'!B14 -> 557.15 | D34: ='Adani Total Gas Stock Price His'!J14 -> 13700000 | I34: =CAPM!C12 -> -0.060663173 | J34: =CAPM!D12 -> -0.14346573 | K34: =CAPM!E12 -> 0.0055191667 | L34: =(J34-K34) -> -0.1489849 | M34: =(I34-K34) -> -0.066182339
B35: ='Adani Total Gas Stock Price His'!A15 -> 45658 | C35: ='Adani Total Gas Stock Price His'!B15 -> 643.1 | D35: ='Adani Total Gas Stock Price His'!J15 -> 35320000 | I35: =CAPM!C13 -> -0.0057854135 | J35: =CAPM!D13 -> -0.16839883 | K35: =CAPM!E13 -> 0.0055191667 | L35: =(J35-K35) -> -0.17391799 | M35: =(I35-K35) -> -0.01130458
B36: ='Adani Total Gas Stock Price His'!A16 -> 45303 | C36: ='Adani Total Gas Stock Price His'!B16 -> 761.05 | D36: ='Adani Total Gas Stock Price His'!J16 -> 37420000 | I36: =CAPM!C14 -> -0.020358247 | J36: =CAPM!D14 -> -0.065232223 | K36: =CAPM!E14 -> 0.0055191667 | L36: =(J36-K36) -> -0.07075139 | M36: =(I36-K36) -> -0.025877414
B37: ='Adani Total Gas Stock Price His'!A17 -> 45302 | C37: ='Adani Total Gas Stock Price His'!B17 -> 812.35 | D37: ='Adani Total Gas Stock Price His'!J17 -> 73230000 | I37: =CAPM!C15 -> -0.0030722181 | J37: =CAPM!D15 -> 0.12297437 | K37: =CAPM!E15 -> 0.0055191667 | L37: =(J37-K37) -> 0.1174552 | M37: =(I37-K37) -> -0.0085913848
B38: ='Adani Total Gas Stock Price His'!A18 -> 45301 | C38: ='Adani Total Gas Stock Price His'!B18 -> 718.35 | D38: ='Adani Total Gas Stock Price His'!J18 -> 14430000 | I38: =CAPM!C16 -> -0.064221263 | J38: =CAPM!D16 -> -0.090635807 | K38: =CAPM!E16 -> 0.0055191667 | L38: =(J38-K38) -> -0.096154974 | M38: =(I38-K38) -> -0.06974043 | O38: 5 Year | Y38: 3 Year
B39: ='Adani Total Gas Stock Price His'!A19 -> 45300 | C39: ='Adani Total Gas Stock Price His'!B19 -> 786.5 | D39: ='Adani Total Gas Stock Price His'!J19 -> 28750000 | I39: =CAPM!C17 -> 0.022527362 | J39: =CAPM!D17 -> -0.054254576 | K39: =CAPM!E17 -> 0.0055191667 | L39: =(J39-K39) -> -0.059773743 | M39: =(I39-K39) -> 0.017008196 | O39: SUMMARY OUTPUT | Y39: SUMMARY OUTPUT
B40: ='Adani Total Gas Stock Price His'!A20 -> 45299 | C40: ='Adani Total Gas Stock Price His'!B20 -> 830.35 | D40: ='Adani Total Gas Stock Price His'!J20 -> 82290000 | I40: =CAPM!C18 -> 0.011347671 | J40: =CAPM!D18 -> -0.075590756 | K40: =CAPM!E18 -> 0.0055191667 | L40: =(J40-K40) -> -0.081109923 | M40: =(I40-K40) -> 0.0058285039
B41: ='Adani Total Gas Stock Price His'!A21 -> 45298 | C41: ='Adani Total Gas Stock Price His'!B21 -> 895.55 | D41: ='Adani Total Gas Stock Price His'!J21 -> 45980000 | I41: =CAPM!C19 -> 0.038424514 | J41: =CAPM!D19 -> -0.0005023583 | K41: =CAPM!E19 -> 0.0055191667 | L41: =(J41-K41) -> -0.006021525 | M41: =(I41-K41) -> 0.032905347 | O41: Regression Statistics | Y41: Regression Statistics
B42: ='Adani Total Gas Stock Price His'!A22 -> 45297 | C42: ='Adani Total Gas Stock Price His'!B22 -> 896 | D42: ='Adani Total Gas Stock Price His'!J22 -> 50780000 | I42: =CAPM!C20 -> 0.063616576 | J42: =CAPM!D20 -> -0.14836228 | K42: =CAPM!E20 -> 0.0055191667 | L42: =(J42-K42) -> -0.15388144 | M42: =(I42-K42) -> 0.058097409 | O42: Multiple R | P42: 0.41321227 | Y42: Multiple R | Z42: 0.38432864
B43: ='Adani Total Gas Stock Price His'!A23 -> 45296 | C43: ='Adani Total Gas Stock Price His'!B23 -> 1039.3 | D43: ='Adani Total Gas Stock Price His'!J23 -> 45820000 | I43: =CAPM!C21 -> -0.0032856614 | J43: =CAPM!D21 -> 0.11208631 | K43: =CAPM!E21 -> 0.0055191667 | L43: =(J43-K43) -> 0.10656715 | M43: =(I43-K43) -> -0.008804828 | O43: R Square | P43: 0.17074438 | Y43: R Square | Z43: 0.14770851
B44: ='Adani Total Gas Stock Price His'!A24 -> 45295 | C44: ='Adani Total Gas Stock Price His'!B24 -> 929.1 | D44: ='Adani Total Gas Stock Price His'!J24 -> 26690000 | I44: =CAPM!C22 -> 0.012372256 | J44: =CAPM!D22 -> 0.0027483648 | K44: =CAPM!E22 -> 0.0055191667 | L44: =(J44-K44) -> -0.0027708018 | M44: =(I44-K44) -> 0.0068530888 | O44: Adjusted R Square | P44: 0.15619604 | Y44: Adjusted R Square | Z44: 0.12264111
B45: ='Adani Total Gas Stock Price His'!A25 -> 45294 | C45: ='Adani Total Gas Stock Price His'!B25 -> 926.55 | D45: ='Adani Total Gas Stock Price His'!J25 -> 59830000 | I45: =CAPM!C23 -> 0.0155319 | J45: =CAPM!D23 -> -0.10161383 | K45: =CAPM!E23 -> 0.0055191667 | L45: =(J45-K45) -> -0.10713299 | M45: =(I45-K45) -> 0.010012733 | O45: Standard Error | P45: 0.21858626 | Y45: Standard Error | Z45: 0.226321
B46: ='Adani Total Gas Stock Price His'!A26 -> 45293 | C46: ='Adani Total Gas Stock Price His'!B26 -> 1025.65 | D46: ='Adani Total Gas Stock Price His'!J26 -> 75130000 | I46: =CAPM!C24 -> 0.011764438 | J46: =CAPM!D24 -> 0.013052197 | K46: =CAPM!E24 -> 0.0055191667 | L46: =(J46-K46) -> 0.0075330304 | M46: =(I46-K46) -> 0.0062452712 | O46: Observations | P46: 59 | Y46: Observations | Z46: 36
B47: ='Adani Total Gas Stock Price His'!A27 -> 45292 | C47: ='Adani Total Gas Stock Price His'!B27 -> 1012.35 | D47: ='Adani Total Gas Stock Price His'!J27 -> 59320000 | I47: =CAPM!C25 -> -0.00026232768 | J47: =CAPM!D25 -> 0.024397551 | K47: =CAPM!E25 -> 0.0055191667 | L47: =(J47-K47) -> 0.018878384 | M47: =(I47-K47) -> -0.0057814943
B48: ='Adani Total Gas Stock Price His'!A28 -> 44938 | C48: ='Adani Total Gas Stock Price His'!B28 -> 987.95 | D48: ='Adani Total Gas Stock Price His'!J28 -> 147010000 | I48: =CAPM!C26 -> 0.076390509 | J48: =CAPM!D26 -> 0.33205869 | K48: =CAPM!E26 -> 0.0055191667 | L48: =(J48-K48) -> 0.32653952 | M48: =(I48-K48) -> 0.070871342 | O48: ANOVA | Y48: ANOVA
B49: ='Adani Total Gas Stock Price His'!A29 -> 44937 | C49: ='Adani Total Gas Stock Price His'!B29 -> 708.8 | D49: ='Adani Total Gas Stock Price His'!J29 -> 41740000 | I49: =CAPM!C27 -> 0.053748009 | J49: =CAPM!D27 -> 0.22798737 | K49: =CAPM!E27 -> 0.0055191667 | L49: =(J49-K49) -> 0.22246821 | M49: =(I49-K49) -> 0.048228842 | P49: df | Q49: SS | R49: MS | S49: F | T49: Significance F | Z49: df | AA49: SS | AB49: MS | AC49: F | AD49: Significance F
B50: ='Adani Total Gas Stock Price His'!A30 -> 44936 | C50: ='Adani Total Gas Stock Price His'!B30 -> 564.3 | D50: ='Adani Total Gas Stock Price His'!J30 -> 20850000 | I50: =CAPM!C28 -> -0.02886204 | J50: =CAPM!D28 -> -0.083186658 | K50: =CAPM!E28 -> 0.0055191667 | L50: =(J50-K50) -> -0.088705825 | M50: =(I50-K50) -> -0.034381206 | O50: Regression | P50: 1 | Q50: 0.560762 | R50: 0.560762 | S50: 11.736345 | T50: 0.0011430593 | Y50: Regression | Z50: 1 | AA50: 0.30181858 | AB50: 0.30181858 | AC50: 5.8924549 | AD50: 0.020652825
B51: ='Adani Total Gas Stock Price His'!A31 -> 44935 | C51: ='Adani Total Gas Stock Price His'!B31 -> 613.25 | D51: ='Adani Total Gas Stock Price His'!J31 -> 11520000 | I51: =CAPM!C29 -> 0.019773297 | J51: =CAPM!D29 -> -0.036111365 | K51: =CAPM!E29 -> 0.0055191667 | L51: =(J51-K51) -> -0.041630532 | M51: =(I51-K51) -> 0.014254131 | O51: Residual | P51: 57 | Q51: 2.7234573 | R51: 0.047779953 | Y51: Residual | Z51: 34 | AA51: 1.7415206 | AB51: 0.051221194
B52: ='Adani Total Gas Stock Price His'!A32 -> 44934 | C52: ='Adani Total Gas Stock Price His'!B32 -> 635.8 | D52: ='Adani Total Gas Stock Price His'!J32 -> 17620000 | I52: =CAPM!C30 -> -0.025637434 | J52: =CAPM!D30 -> -0.042946192 | K52: =CAPM!E30 -> 0.0055191667 | L52: =(J52-K52) -> -0.048465358 | M52: =(I52-K52) -> -0.031156601 | O52: Total | P52: 58 | Q52: 3.2842193 | Y52: Total | Z52: 35 | AA52: 2.0433392
B53: ='Adani Total Gas Stock Price His'!A33 -> 44933 | C53: ='Adani Total Gas Stock Price His'!B33 -> 663.7 | D53: ='Adani Total Gas Stock Price His'!J33 -> 14970000 | I53: =CAPM!C31 -> 0.029006074 | J53: =CAPM!D31 -> 0.013805878 | K53: =CAPM!E31 -> 0.0055191667 | L53: =(J53-K53) -> 0.0082867114 | M53: =(I53-K53) -> 0.023486907
B54: ='Adani Total Gas Stock Price His'!A34 -> 44932 | C54: ='Adani Total Gas Stock Price His'!B34 -> 654.6 | D54: ='Adani Total Gas Stock Price His'!J34 -> 45130000 | I54: =CAPM!C32 -> 0.034711339 | J54: =CAPM!D32 -> -0.014483666 | K54: =CAPM!E32 -> 0.0055191667 | L54: =(J54-K54) -> -0.020002832 | M54: =(I54-K54) -> 0.029192172 | P54: Coefficients | Q54: Standard Error | R54: t Stat | S54: P-value | T54: Lower 95% | U54: Upper 95% | V54: Lower 95.0% | W54: Upper 95.0% | Z54: Coefficients | AA54: Standard Error | AB54: t Stat | AC54: P-value | AD54: Lower 95% | AE54: Upper 95% | AF54: Lower 95.0% | AG54: Upper 95.0%
B55: ='Adani Total Gas Stock Price His'!A35 -> 44931 | C55: ='Adani Total Gas Stock Price His'!B35 -> 664.15 | D55: ='Adani Total Gas Stock Price His'!J35 -> 80520000 | I55: =CAPM!C33 -> 0.0256521 | J55: =CAPM!D33 -> -0.3526769 | K55: =CAPM!E33 -> 0.0055191667 | L55: =(J55-K55) -> -0.35819607 | M55: =(I55-K55) -> 0.020132934 | O55: Intercept | P55: -0.014051407 | Q55: 0.028803986 | R55: -0.48782857 | S55: 0.62754249 | T55: -0.071730394 | U55: 0.043627579 | V55: -0.071730394 | W55: 0.043627579 | Y55: Intercept | Z55: -0.07097717 | AA55: 0.03812157 | AB55: -1.8618638 | AC55: 0.07128455 | AD55: -0.14844952 | AE55: 0.0064951805 | AF55: -0.14844952 | AG55: 0.0064951805
B56: ='Adani Total Gas Stock Price His'!A36 -> 44930 | C56: ='Adani Total Gas Stock Price His'!B36 -> 945 | D56: ='Adani Total Gas Stock Price His'!J36 -> 14500000 | I56: =CAPM!C34 -> 0.039822056 | J56: =CAPM!D34 -> 0.085281273 | K56: =CAPM!E34 -> 0.0055191667 | L56: =(J56-K56) -> 0.079762106 | M56: =(I56-K56) -> 0.03430289 | O56: X Variable 1 | P56: 2.7716321 | Q56: 0.80903842 | R56: 3.4258349 | S56: 0.0011430593 | T56: 1.1515606 | U56: 4.3917036 | V56: 1.1515606 | W56: 4.3917036 | Y56: X Variable 1 | Z56: 2.8670556 | AA56: 1.1811036 | AB56: 2.4274379 | AC56: 0.020652825 | AD56: 0.46676437 | AE56: 5.2673469 | AF56: 0.46676437 | AG56: 5.2673469
B57: ='Adani Total Gas Stock Price His'!A37 -> 44929 | C57: ='Adani Total Gas Stock Price His'!B37 -> 867.75 | D57: ='Adani Total Gas Stock Price His'!J37 -> 53410000 | I57: =CAPM!C35 -> 0.0032195091 | J57: =CAPM!D35 -> 0.24594549 | K57: =CAPM!E35 -> 0.0055191667 | L57: =(J57-K57) -> 0.24042632 | M57: =(I57-K57) -> -0.0022996576
B58: ='Adani Total Gas Stock Price His'!A38 -> 44928 | C58: ='Adani Total Gas Stock Price His'!B38 -> 678.55 | D58: ='Adani Total Gas Stock Price His'!J38 -> 14930000 | I58: =CAPM!C36 -> -0.020489133 | J58: =CAPM!D36 -> -1.1336316 | K58: =CAPM!E36 -> 0.0055191667 | L58: =(J58-K58) -> -1.1391508 | M58: =(I58-K58) -> -0.026008299
B59: ='Adani Total Gas Stock Price His'!A39 -> 44927 | C59: ='Adani Total Gas Stock Price His'!B39 -> 2108.2 | D59: ='Adani Total Gas Stock Price His'!J39 -> 11390000 | I59: =CAPM!C37 -> -0.024780781 | J59: =CAPM!D37 -> -0.56056401 | K59: =CAPM!E37 -> 0.0055191667 | L59: =(J59-K59) -> -0.56608318 | M59: =(I59-K59) -> -0.030299948
B60: ='Adani Total Gas Stock Price His'!A40 -> 44573 | C60: ='Adani Total Gas Stock Price His'!B40 -> 3692.85 | D60: ='Adani Total Gas Stock Price His'!J40 -> 7010000 | I60: =CAPM!C38 -> -0.035434274 | J60: =CAPM!D38 -> 0.01640858 | K60: =CAPM!E38 -> 0.0055191667 | L60: =(J60-K60) -> 0.010889414 | M60: =(I60-K60) -> -0.04095344 | O60: RESIDUAL OUTPUT | Y60: RESIDUAL OUTPUT
B61: ='Adani Total Gas Stock Price His'!A41 -> 44572 | C61: ='Adani Total Gas Stock Price His'!B41 -> 3632.75 | D61: ='Adani Total Gas Stock Price His'!J41 -> 5960000 | I61: =CAPM!C39 -> 0.040589681 | J61: =CAPM!D39 -> 0.0082647383 | K61: =CAPM!E39 -> 0.0055191667 | L61: =(J61-K61) -> 0.0027455716 | M61: =(I61-K61) -> 0.035070514
B62: ='Adani Total Gas Stock Price His'!A42 -> 44571 | C62: ='Adani Total Gas Stock Price His'!B42 -> 3602.85 | D62: ='Adani Total Gas Stock Price His'!J42 -> 6480000 | I62: =CAPM!C40 -> 0.052301307 | J62: =CAPM!D40 -> 0.075799303 | K62: =CAPM!E40 -> 0.0055191667 | L62: =(J62-K62) -> 0.070280136 | M62: =(I62-K62) -> 0.04678214 | O62: Observation | P62: Predicted Y | Q62: Residuals | Y62: Observation | Z62: Predicted Y | AA62: Residuals
B63: ='Adani Total Gas Stock Price His'!A43 -> 44570 | C63: ='Adani Total Gas Stock Price His'!B43 -> 3339.85 | D63: ='Adani Total Gas Stock Price His'!J43 -> 9390000 | I63: =CAPM!C41 -> -0.038161323 | J63: =CAPM!D41 -> -0.11448237 | K63: =CAPM!E41 -> 0.0055191667 | L63: =(J63-K63) -> -0.12000154 | M63: =(I63-K63) -> -0.043680489 | O63: 1 | P63: -0.037118024 | Q63: -0.036523098 | Y63: 1 | Z63: -0.09483794 | AA63: 0.021196818
B64: ='Adani Total Gas Stock Price His'!A44 -> 44569 | C64: ='Adani Total Gas Stock Price His'!B44 -> 3744.95 | D64: ='Adani Total Gas Stock Price His'!J44 -> 9980000 | I64: =CAPM!C42 -> 0.034430215 | J64: =CAPM!D42 -> 0.18027023 | K64: =CAPM!E42 -> 0.0055191667 | L64: =(J64-K64) -> 0.17475106 | M64: =(I64-K64) -> 0.028911048 | O64: 2 | P64: 0.021986153 | Q64: -0.067809584 | Y64: 2 | Z64: -0.033698885 | AA64: -0.012124546
B65: ='Adani Total Gas Stock Price His'!A45 -> 44568 | C65: ='Adani Total Gas Stock Price His'!B45 -> 3127.2 | D65: ='Adani Total Gas Stock Price His'!J45 -> 9510000 | I65: =CAPM!C43 -> 0.083719949 | J65: =CAPM!D43 -> 0.26763202 | K65: =CAPM!E43 -> 0.0055191667 | L65: =(J65-K65) -> 0.26211285 | M65: =(I65-K65) -> 0.078200783 | O65: 3 | P65: 0.09302732 | Q65: -0.088521739 | Y65: 3 | Z65: 0.039788133 | AA65: -0.035282552
B66: ='Adani Total Gas Stock Price His'!A46 -> 44567 | C66: ='Adani Total Gas Stock Price His'!B46 -> 2392.9 | D66: ='Adani Total Gas Stock Price His'!J46 -> 11700000 | I66: =CAPM!C44 -> -0.049712381 | J66: =CAPM!D44 -> -0.0020873348 | K66: =CAPM!E44 -> 0.0055191667 | L66: =(J66-K66) -> -0.0076065015 | M66: =(I66-K66) -> -0.055231548 | O66: 4 | P66: -0.0085207348 | Q66: 0.059247895 | Y66: 4 | Z66: -0.065256084 | AA66: 0.11598324
B67: ='Adani Total Gas Stock Price His'!A47 -> 44566 | C67: ='Adani Total Gas Stock Price His'!B47 -> 2397.9 | D67: ='Adani Total Gas Stock Price His'!J47 -> 8870000 | I67: =CAPM!C45 -> -0.030756036 | J67: =CAPM!D45 -> -0.02188235 | K67: =CAPM!E45 -> 0.0055191667 | L67: =(J67-K67) -> -0.027401517 | M67: =(I67-K67) -> -0.036275203 | O67: 5 | P67: -0.067828991 | Q67: 0.040555285 | Y67: 5 | Z67: -0.12660624 | AA67: 0.099332537
B68: ='Adani Total Gas Stock Price His'!A48 -> 44565 | C68: ='Adani Total Gas Stock Price His'!B48 -> 2450.95 | D68: ='Adani Total Gas Stock Price His'!J48 -> 7290000 | I68: =CAPM!C46 -> -0.020956989 | J68: =CAPM!D46 -> 0.13110089 | K68: =CAPM!E46 -> 0.0055191667 | L68: =(J68-K68) -> 0.12558172 | M68: =(I68-K68) -> -0.026476155 | O68: 6 | P68: -0.11188834 | Q68: -0.0057142639 | Y68: 6 | Z68: -0.1721825 | AA68: 0.054579893
B69: ='Adani Total Gas Stock Price His'!A49 -> 44564 | C69: ='Adani Total Gas Stock Price His'!B49 -> 2149.8 | D69: ='Adani Total Gas Stock Price His'!J49 -> 5680000 | I69: =CAPM!C47 -> 0.039168839 | J69: =CAPM!D47 -> 0.30258464 | K69: =CAPM!E47 -> 0.0055191667 | L69: =(J69-K69) -> 0.29706547 | M69: =(I69-K69) -> 0.033649672 | O69: 7 | P69: 0.055167105 | Q69: -0.072455441 | Y69: 7 | Z69: 0.00062444263 | AA69: -0.017912778
B70: ='Adani Total Gas Stock Price His'!A50 -> 44563 | C70: ='Adani Total Gas Stock Price His'!B50 -> 1588.5 | D70: ='Adani Total Gas Stock Price His'!J50 -> 3520000 | I70: =CAPM!C48 -> -0.031991596 | J70: =CAPM!D48 -> -0.1367329 | K70: =CAPM!E48 -> 0.0055191667 | L70: =(J70-K70) -> -0.14225207 | M70: =(I70-K70) -> -0.037510762 | O70: 8 | P70: 0.01768887 | Q70: 0.10712138 | Y70: 8 | Z70: -0.038144118 | AA70: 0.16295437
B71: ='Adani Total Gas Stock Price His'!A51 -> 44562 | C71: ='Adani Total Gas Stock Price His'!B51 -> 1821.25 | D71: ='Adani Total Gas Stock Price His'!J51 -> 3910000 | I71: =CAPM!C49 -> -0.00081858775 | J71: =CAPM!D49 -> 0.056152823 | K71: =CAPM!E49 -> 0.0055191667 | L71: =(J71-K71) -> 0.050633657 | M71: =(I71-K71) -> -0.0063377544 | O71: 9 | P71: 0.065051291 | Q71: -0.074561151 | Y71: 9 | Z71: 0.010848928 | AA71: -0.020358788
B72: ='Adani Total Gas Stock Price His'!A52 -> 44208 | C72: ='Adani Total Gas Stock Price His'!B52 -> 1721.8 | D72: ='Adani Total Gas Stock Price His'!J52 -> 4450000 | I72: =CAPM!C50 -> 0.021601288 | J72: =CAPM!D50 -> 0.07346038 | K72: =CAPM!E50 -> 0.0055191667 | L72: =(J72-K72) -> 0.067941214 | M72: =(I72-K72) -> 0.016082122 | O72: 10 | P72: 0.14007819 | Q72: -0.067178233 | Y72: 10 | Z72: 0.088458901 | AA72: -0.015558944
B73: ='Adani Total Gas Stock Price His'!A53 -> 44207 | C73: ='Adani Total Gas Stock Price His'!B53 -> 1599.85 | D73: ='Adani Total Gas Stock Price His'!J53 -> 8940000 | I73: =CAPM!C51 -> -0.03973704 | J73: =CAPM!D51 -> 0.10564878 | K73: =CAPM!E51 -> 0.0055191667 | L73: =(J73-K73) -> 0.10012961 | M73: =(I73-K73) -> -0.045256207 | O73: 11 | P73: -0.1974845 | Q73: 0.048499605 | Y73: 11 | Z73: -0.26072562 | AA73: 0.11174072
B74: ='Adani Total Gas Stock Price His'!A54 -> 44206 | C74: ='Adani Total Gas Stock Price His'!B54 -> 1439.45 | D74: ='Adani Total Gas Stock Price His'!J54 -> 8030000 | I74: =CAPM!C52 -> 0.0030320399 | J74: =CAPM!D52 -> 0.011388372 | K74: =CAPM!E52 -> 0.0055191667 | L74: =(J74-K74) -> 0.0058692049 | M74: =(I74-K74) -> -0.0024871268 | O74: 12 | P74: -0.045383544 | Q74: -0.12853445 | Y74: 12 | Z74: -0.10338803 | AA74: -0.070529962
... B82: ='Adani Total Gas Stock Price His'!A62 -> 44198 | C82: ='Adani Total Gas Stock Price His'!B62 -> 512.2 | D82: ='Adani Total Gas Stock Price His'!J62 -> 42810000 | I82: =CAPM!C60 -> 0.063546297 | J82: =CAPM!D60 -> 0.29578457 | K82: =CAPM!E60 -> 0.0055191667 | L82: =(J82-K82) -> 0.29026541 | M82: =(I82-K82) -> 0.05802713 | O82: 20 | P82: -0.038455151 | Q82: 0.1450223 | Y82: 20 | Z82: -0.096221102 | AA82: 0.20278825
B83: ='Adani Total Gas Stock Price His'!A63 -> 44197 | C83: ='Adani Total Gas Stock Price His'!B63 -> 381.05 | D83: ='Adani Total Gas Stock Price His'!J63 -> 23510000 | O83: 21 | P83: 0.0049428337 | Q83: -0.0077136356 | Y83: 21 | Z83: -0.051328983 | AA83: 0.048558181
O84: 22 | P84: 0.013700206 | Q84: -0.1208332 | Y84: 22 | Z84: -0.042270106 | AA84: -0.064862887
O85: 23 | P85: 0.0032581868 | Q85: 0.0042748436 | Y85: 23 | Z85: -0.05307163 | AA85: 0.06060466
O86: 24 | P86: -0.030075582 | Q86: 0.048953966 | Y86: 24 | Z86: -0.087553036 | AA86: 0.10643142
O87: 25 | P87: 0.18237788 | Q87: 0.14416164 | Y87: 25 | Z87: 0.13221491 | AA87: 0.19432461
O88: 26 | P88: 0.1196212 | Q88: 0.10284701 | Y88: 26 | Z88: 0.067297604 | AA88: 0.1551706
O89: 27 | P89: -0.10934346 | Q89: 0.020637637 | Y89: 27 | Z89: -0.16955 | AA89: 0.080844176
O90: 28 | P90: 0.025455799 | Q90: -0.067086331 | Y90: 28 | Z90: -0.030109784 | AA90: -0.011520748
O91: 29 | P91: -0.10040604 | Q91: 0.051940683 | Y91: 29 | Z91: -0.16030488 | AA91: 0.11183952
O92: 30 | P92: 0.051045659 | Q92: -0.042758947 | Y92: 30 | Z92: -0.0036388997 | AA92: 0.011925611
O93: 31 | P93: 0.066858554 | Q93: -0.086861386 | Y93: 31 | Z93: 0.012718412 | AA93: -0.032721244
O94: 32 | P94: 0.041749677 | Q94: -0.39994574 | Y94: 32 | Z94: -0.013254929 | AA94: -0.34494114
O95: 33 | P95: 0.081023582 | Q95: -0.0012614762 | Y95: 33 | Z95: 0.027371123 | AA95: 0.052390983
... O98: 36 | P98: -0.098031715 | Q98: -0.46805147 | Y98: 36 | Z98: -0.15784881 | AA98: -0.40823438
O99: 37 | P99: -0.12755928 | Q99: 0.13844869
O100: 38 | P100: 0.083151154 | Q100: -0.080405582
O101: 39 | P101: 0.11561147 | Q101: -0.045331336
O102: 40 | P102: -0.13511765 | Q102: 0.015116116
O103: 41 | P103: 0.066079381 | Q103: 0.10867168
O104: 42 | P104: 0.20269239 | Q104: 0.059420459
O105: 43 | P105: -0.16713294 | Q105: 0.15952643
O106: 44 | P106: -0.11459292 | Q106: 0.087191406
O107: 45 | P107: -0.087433568 | Q107: 0.21301529
O108: 46 | P108: 0.079213103 | Q108: 0.21785237
O109: 47 | P109: -0.11801744 | Q109: -0.024234632
O110: 48 | P110: -0.031617331 | Q110: 0.082250987
... O121: 59 | P121: 0.14677845 | Q121: 0.14348696

Sheet DDM
B2: DDM for infinite period returns
B3: Value = PV of all any dividends + PV of the selling price
B4: This is also called the constant growth DDM
B5: Assumes an estimation of future dividend payment for an infinite period
B9: P0 | C9: D1 / (Ke-g)
B10: D1 = D0 X (1+g)
B11: Ke | C11: required return (CAPM output, annual)
B12: g | C12: growth rate (assume 0 because dividends constant)
B14: Label | C14: Value
B15: Latest Dividend (D₀) | C15: ='Dividend '!C3 -> 0.25 | D15: constant for last 5 years
B16: Growth Rate (g) | C16: 0 | D16: g = (Old Dividend / Latest Dividend ) - 1
B17: Next Dividend (D₁) | C17: =C15*(1+C16) -> 0.25 | D17: D1 = D0 X (1+g)
B18: Required Return (kₑ) | C18: =CAPM!E70 -> 0.2493422 | D18: CAPM output
B19: DDM Valuation: Price (P₀) | C19: =C17/(C18-C16) -> 1.0026381 | D19: P0 = D1 / (Ke-g)
B22: g ↓ \ kₑ → | C22: 20% | D22: 22% | E22: 24% | F22: 26% | G22: 28%
B23: 0 | C23: =$C$17/($C$22-$B23) -> 1.25 | D23: =$C$17/($D$22-$B23) -> 1.1363636 | E23: =$C$17/($E$22-$B23) -> 1.0416667 | F23: =$C$17/($F$22-$B23) -> 0.96153846 | G23: =$C$17/($G$22-$B23) -> 0.89285714
B24: 0.01 | C24: =$C$17/($C$22-$B24) -> 1.3157895 | D24: =$C$17/($D$22-$B24) -> 1.1904762 | E24: =$C$17/($E$22-$B24) -> 1.0869565 | F24: =$C$17/($F$22-$B24) -> 1 | G24: =$C$17/($G$22-$B24) -> 0.92592593
B25: 0.02 | C25: =$C$17/($C$22-$B25) -> 1.3888889 | D25: =$C$17/($D$22-$B25) -> 1.25 | E25: =$C$17/($E$22-$B25) -> 1.1363636 | F25: =$C$17/($F$22-$B25) -> 1.0416667 | G25: =$C$17/($G$22-$B25) -> 0.96153846
B26: 0.03 | C26: =$C$17/($C$22-$B26) -> 1.4705882 | D26: =$C$17/($D$22-$B26) -> 1.3157895 | E26: =$C$17/($E$22-$B26) -> 1.1904762 | F26: =$C$17/($F$22-$B26) -> 1.0869565 | G26: =$C$17/($G$22-$B26) -> 1
B27: 0.04 | C27: =$C$17/($C$22-$B27) -> 1.5625 | D27: =$C$17/($D$22-$B27) -> 1.3888889 | E27: =$C$17/($E$22-$B27) -> 1.25 | F27: =$C$17/($F$22-$B27) -> 1.1363636 | G27: =$C$17/($G$22-$B27) -> 1.0416667
B30: Interpret the Results
B31: Current Market Price: 564.15 INR (as of today’s close on 08Jan26).
B32: DDM Valuation: Base case (g = 0%, ke 24.93%) gives 1.00 INR, even optimistic scenarios (g = 4%, ke = 20%) only reach 1.563 INR.
B34: Observation:
B35: DDM valuation is far below the market price because Adani Total Gas pays negligible dividends (0.25 INR annually).
B36: DDM assumes value comes only from dividends, so it undervalues high-growth, low-dividend stocks.
B37: Market price reflects growth expectations and retained earnings, which DDM ignores.

Sheet CAPM
A1: Date | B1: Price | C1: Rm = Ln return | D1: ATGL (Ri) | E1: Rf =10yrs govt bond = 6.623% pa | F1: Er = Rf+(Rm-Rf)*Beta
A2: 45669 | B2: ='Nifty 50 Historical Data'!B4 -> 26129.6 | C2: =LN(B2/B3) -> -0.0028032285 | D2: ='Monthly Vs Risk'!D2 -> -0.068121955 | E2: =Reference!$B$4%/12 -> 0.0055191667 | F2: =E2+(C2-E2)*$J$35 -> -0.017547451 | I2: Definitions
A3: 45668 | B3: ='Nifty 50 Historical Data'!B5 -> 26202.95 | C3: =LN(B3/B4) -> 0.018521455 | D3: ='Monthly Vs Risk'!D3 -> -0.040304264 | E3: =Reference!$B$4%/12 -> 0.0055191667 | F3: =E3+(C3-E3)*$J$35 -> 0.041556727 | I3: CAPM = Er=Rf+(Rm-Rf)Beta
A4: 45667 | B4: ='Nifty 50 Historical Data'!B6 -> 25722.1 | C4: =LN(B4/B5) -> 0.044152984 | D4: ='Monthly Vs Risk'!D4 -> 0.010024748 | E4: =Reference!$B$4%/12 -> 0.0055191667 | F4: =E4+(C4-E4)*$J$35 -> 0.11259789 | I4: Er | J4: Expected return | M4: 10 years govt. bonds rate
A5: 45666 | B5: ='Nifty 50 Historical Data'!B7 -> 24611.1 | C5: =LN(B5/B6) -> 0.0075146236 | D5: ='Monthly Vs Risk'!D5 -> 0.056246327 | E5: =Reference!$B$4%/12 -> 0.0055191667 | F5: =E5+(C5-E5)*$J$35 -> 0.011049839 | I5: Rf | J5: Risk free rate of return
A6: 45665 | B6: ='Nifty 50 Historical Data'!B8 -> 24426.85 | C6: =LN(B6/B7) -> -0.013883691 | D6: ='Monthly Vs Risk'!D6 -> -0.021754539 | E6: =Reference!$B$4%/12 -> 0.0055191667 | F6: =E6+(C6-E6)*$J$35 -> -0.048258417 | I6: Rm | J6: Market return (index rate of return)
A7: 45664 | B7: ='Nifty 50 Historical Data'!B9 -> 24768.35 | C7: =LN(B7/B8) -> -0.029780228 | D7: ='Monthly Vs Risk'!D7 -> -0.11208344 | E7: =Reference!$B$4%/12 -> 0.0055191667 | F7: =E7+(C7-E7)*$J$35 -> -0.092317767 | I7: Rm-Rf | J7: Risk premium | L7: =J35 -> 2.7716321
A8: 45663 | B8: ='Nifty 50 Historical Data'!B10 -> 25517.05 | C8: =LN(B8/B9) -> 0.030493085 | D8: ='Monthly Vs Risk'!D8 -> -0.011769169 | E8: =Reference!$B$4%/12 -> 0.0055191667 | F8: =E8+(C8-E8)*$J$35 -> 0.074737679 | I8: Beta | J8: Equity coefficient
A9: 45662 | B9: ='Nifty 50 Historical Data'!B11 -> 24750.7 | C9: =LN(B9/B10) -> 0.016971003 | D9: ='Monthly Vs Risk'!D9 -> 0.13032942 | E9: =Reference!$B$4%/12 -> 0.0055191667 | F9: =E9+(C9-E9)*$J$35 -> 0.037259444 | I9: Linear Reggression = Y = a+bx
A10: 45661 | B10: ='Nifty 50 Historical Data'!B12 -> 24334.2 | C10: =LN(B10/B11) -> 0.034059282 | D10: ='Monthly Vs Risk'!D10 -> -0.0039906937 | E10: =Reference!$B$4%/12 -> 0.0055191667 | F10: =E10+(C10-E10)*$J$35 -> 0.084621865
A11: 45660 | B11: ='Nifty 50 Historical Data'!B13 -> 23519.35 | C11: =LN(B11/B12) -> 0.061128855 | D11: ='Monthly Vs Risk'!D11 -> 0.078419123 | E11: =Reference!$B$4%/12 -> 0.0055191667 | F11: =E11+(C11-E11)*$J$35 -> 0.15964876
A12: 45659 | B12: ='Nifty 50 Historical Data'!B14 -> 22124.7 | C12: =LN(B12/B13) -> -0.060663173 | D12: ='Monthly Vs Risk'!D12 -> -0.14346573 | E12: =Reference!$B$4%/12 -> 0.0055191667 | F12: =E12+(C12-E12)*$J$35 -> -0.17791393
A13: 45658 | B13: ='Nifty 50 Historical Data'!B15 -> 23508.4 | C13: =LN(B13/B14) -> -0.0057854135 | D13: ='Monthly Vs Risk'!D13 -> -0.16839883 | E13: =Reference!$B$4%/12 -> 0.0055191667 | F13: =E13+(C13-E13)*$J$35 -> -0.02581297
A14: 45303 | B14: ='Nifty 50 Historical Data'!B16 -> 23644.8 | C14: =LN(B14/B15) -> -0.020358247 | D14: ='Monthly Vs Risk'!D14 -> -0.065232223 | E14: =Reference!$B$4%/12 -> 0.0055191667 | F14: =E14+(C14-E14)*$J$35 -> -0.066203504 | G14: kk
A15: 45302 | B15: ='Nifty 50 Historical Data'!B17 -> 24131.1 | C15: =LN(B15/B16) -> -0.0030722181 | D15: ='Monthly Vs Risk'!D15 -> 0.12297437 | E15: =Reference!$B$4%/12 -> 0.0055191667 | F15: =E15+(C15-E15)*$J$35 -> -0.018292991
A16: 45301 | B16: ='Nifty 50 Historical Data'!B18 -> 24205.35 | C16: =LN(B16/B17) -> -0.064221263 | D16: ='Monthly Vs Risk'!D16 -> -0.090635807 | E16: =Reference!$B$4%/12 -> 0.0055191667 | F16: =E16+(C16-E16)*$J$35 -> -0.18777565
A17: 45300 | B17: ='Nifty 50 Historical Data'!B19 -> 25810.85 | C17: =LN(B17/B18) -> 0.022527362 | D17: ='Monthly Vs Risk'!D17 -> -0.054254576 | E17: =Reference!$B$4%/12 -> 0.0055191667 | F17: =E17+(C17-E17)*$J$35 -> 0.052659627
A18: 45299 | B18: ='Nifty 50 Historical Data'!B20 -> 25235.9 | C18: =LN(B18/B19) -> 0.011347671 | D18: ='Monthly Vs Risk'!D18 -> -0.075590756 | E18: =Reference!$B$4%/12 -> 0.0055191667 | F18: =E18+(C18-E18)*$J$35 -> 0.021673635
A19: 45298 | B19: ='Nifty 50 Historical Data'!B21 -> 24951.15 | C19: =LN(B19/B20) -> 0.038424514 | D19: ='Monthly Vs Risk'!D19 -> -0.0005023583 | E19: =Reference!$B$4%/12 -> 0.0055191667 | F19: =E19+(C19-E19)*$J$35 -> 0.096720682
A20: 45297 | B20: ='Nifty 50 Historical Data'!B22 -> 24010.6 | C20: =LN(B20/B21) -> 0.063616576 | D20: ='Monthly Vs Risk'!D20 -> -0.14836228 | E20: =Reference!$B$4%/12 -> 0.0055191667 | F20: =E20+(C20-E20)*$J$35 -> 0.16654381 | I20: Regression Statistics
A21: 45296 | B21: ='Nifty 50 Historical Data'!B23 -> 22530.7 | C21: =LN(B21/B22) -> -0.0032856614 | D21: ='Monthly Vs Risk'!D21 -> 0.11208631 | E21: =Reference!$B$4%/12 -> 0.0055191667 | F21: =E21+(C21-E21)*$J$35 -> -0.018884577 | I21: Multiple R | J21: 0.41321227
A22: 45295 | B22: ='Nifty 50 Historical Data'!B24 -> 22604.85 | C22: =LN(B22/B23) -> 0.012372256 | D22: ='Monthly Vs Risk'!D22 -> 0.0027483648 | E22: =Reference!$B$4%/12 -> 0.0055191667 | F22: =E22+(C22-E22)*$J$35 -> 0.024513407 | I22: R Square | J22: 0.17074438
A23: 45294 | B23: ='Nifty 50 Historical Data'!B25 -> 22326.9 | C23: =LN(B23/B24) -> 0.0155319 | D23: ='Monthly Vs Risk'!D23 -> -0.10161383 | E23: =Reference!$B$4%/12 -> 0.0055191667 | F23: =E23+(C23-E23)*$J$35 -> 0.03327078 | I23: Adjusted R Square | J23: 0.15619604
A24: 45293 | B24: ='Nifty 50 Historical Data'!B26 -> 21982.8 | C24: =LN(B24/B25) -> 0.011764438 | D24: ='Monthly Vs Risk'!D24 -> 0.013052197 | E24: =Reference!$B$4%/12 -> 0.0055191667 | F24: =E24+(C24-E24)*$J$35 -> 0.022828761 | I24: Standard Error | J24: 0.21858626
A25: 45292 | B25: ='Nifty 50 Historical Data'!B27 -> 21725.7 | C25: =LN(B25/B26) -> -0.00026232768 | D25: ='Monthly Vs Risk'!D25 -> 0.024397551 | E25: =Reference!$B$4%/12 -> 0.0055191667 | F25: =E25+(C25-E25)*$J$35 -> -0.010505008 | I25: Observations | J25: 59
A26: 44938 | B26: ='Nifty 50 Historical Data'!B28 -> 21731.4 | C26: =LN(B26/B27) -> 0.076390509 | D26: ='Monthly Vs Risk'!D26 -> 0.33205869 | E26: =Reference!$B$4%/12 -> 0.0055191667 | F26: =E26+(C26-E26)*$J$35 -> 0.20194845
A27: 44937 | B27: ='Nifty 50 Historical Data'!B29 -> 20133.15 | C27: =LN(B27/B28) -> 0.053748009 | D27: ='Monthly Vs Risk'!D27 -> 0.22798737 | E27: =Reference!$B$4%/12 -> 0.0055191667 | F27: =E27+(C27-E27)*$J$35 -> 0.13919177 | I27: ANOVA
A28: 44936 | B28: ='Nifty 50 Historical Data'!B30 -> 19079.6 | C28: =LN(B28/B29) -> -0.02886204 | D28: ='Monthly Vs Risk'!D28 -> -0.083186658 | E28: =Reference!$B$4%/12 -> 0.0055191667 | F28: =E28+(C28-E28)*$J$35 -> -0.089772888 | J28: df | K28: SS | L28: MS | M28: F | N28: Significance F
A29: 44935 | B29: ='Nifty 50 Historical Data'!B31 -> 19638.3 | C29: =LN(B29/B30) -> 0.019773297 | D29: ='Monthly Vs Risk'!D29 -> -0.036111365 | E29: =Reference!$B$4%/12 -> 0.0055191667 | F29: =E29+(C29-E29)*$J$35 -> 0.045026372 | I29: Regression | J29: 1 | K29: 0.560762 | L29: 0.560762 | M29: 11.736345 | N29: 0.0011430593
A30: 44934 | B30: ='Nifty 50 Historical Data'!B32 -> 19253.8 | C30: =LN(B30/B31) -> -0.025637434 | D30: ='Monthly Vs Risk'!D30 -> -0.042946192 | E30: =Reference!$B$4%/12 -> 0.0055191667 | F30: =E30+(C30-E30)*$J$35 -> -0.080835467 | I30: Residual | J30: 57 | K30: 2.7234573 | L30: 0.047779953
A31: 44933 | B31: ='Nifty 50 Historical Data'!B33 -> 19753.8 | C31: =LN(B31/B32) -> 0.029006074 | D31: ='Monthly Vs Risk'!D31 -> 0.013805878 | E31: =Reference!$B$4%/12 -> 0.0055191667 | F31: =E31+(C31-E31)*$J$35 -> 0.070616233 | I31: Total | J31: 58 | K31: 3.2842193
A32: 44932 | B32: ='Nifty 50 Historical Data'!B34 -> 19189.05 | C32: =LN(B32/B33) -> 0.034711339 | D32: ='Monthly Vs Risk'!D32 -> -0.014483666 | E32: =Reference!$B$4%/12 -> 0.0055191667 | F32: =E32+(C32-E32)*$J$35 -> 0.086429128
A33: 44931 | B33: ='Nifty 50 Historical Data'!B35 -> 18534.4 | C33: =LN(B33/B34) -> 0.0256521 | D33: ='Monthly Vs Risk'!D33 -> -0.3526769 | E33: =Reference!$B$4%/12 -> 0.0055191667 | F33: =E33+(C33-E33)*$J$35 -> 0.061320251 | J33: Coefficients | K33: Standard Error | L33: t Stat | M33: P-value | N33: Lower 95% | O33: Upper 95% | P33: Lower 95.0% | Q33: Upper 95.0%
A34: 44930 | B34: ='Nifty 50 Historical Data'!B36 -> 18065 | C34: =LN(B34/B35) -> 0.039822056 | D34: ='Monthly Vs Risk'!D34 -> 0.085281273 | E34: =Reference!$B$4%/12 -> 0.0055191667 | F34: =E34+(C34-E34)*$J$35 -> 0.10059416 | I34: Intercept | J34: -0.02382934 | K34: 0.02982257 | L34: -0.79903709 | M34: 0.42758597 | N34: -0.083548007 | O34: 0.035889327 | P34: -0.083548007 | Q34: 0.035889327
A35: 44929 | B35: ='Nifty 50 Historical Data'!B37 -> 17359.75 | C35: =LN(B35/B36) -> 0.0032195091 | D35: ='Monthly Vs Risk'!D35 -> 0.24594549 | E35: =Reference!$B$4%/12 -> 0.0055191667 | F35: =E35+(C35-E35)*$J$35 -> -0.0008546381 | I35: Beta | J35: 2.7716321 | K35: 0.80903842 | L35: 3.4258349 | M35: 0.0011430593 | N35: 1.1515606 | O35: 4.3917036 | P35: 1.1515606 | Q35: 4.3917036
A36: 44928 | B36: ='Nifty 50 Historical Data'!B38 -> 17303.95 | C36: =LN(B36/B37) -> -0.020489133 | D36: ='Monthly Vs Risk'!D36 -> -1.1336316 | E36: =Reference!$B$4%/12 -> 0.0055191667 | F36: =E36+(C36-E36)*$J$35 -> -0.06656627
A37: 44927 | B37: ='Nifty 50 Historical Data'!B39 -> 17662.15 | C37: =LN(B37/B38) -> -0.024780781 | D37: ='Monthly Vs Risk'!D37 -> -0.56056401 | E37: =Reference!$B$4%/12 -> 0.0055191667 | F37: =E37+(C37-E37)*$J$35 -> -0.078461141
A38: 44573 | B38: ='Nifty 50 Historical Data'!B40 -> 18105.3 | C38: =LN(B38/B39) -> -0.035434274 | D38: ='Monthly Vs Risk'!D38 -> 0.01640858 | E38: =Reference!$B$4%/12 -> 0.0055191667 | F38: =E38+(C38-E38)*$J$35 -> -0.1079887
A39: 44572 | B39: ='Nifty 50 Historical Data'!B41 -> 18758.35 | C39: =LN(B39/B40) -> 0.040589681 | D39: ='Monthly Vs Risk'!D39 -> 0.0082647383 | E39: =Reference!$B$4%/12 -> 0.0055191667 | F39: =E39+(C39-E39)*$J$35 -> 0.10272173 | I39: RESIDUAL OUTPUT
A40: 44571 | B40: ='Nifty 50 Historical Data'!B42 -> 18012.2 | C40: =LN(B40/B41) -> 0.052301307 | D40: ='Monthly Vs Risk'!D40 -> 0.075799303 | E40: =Reference!$B$4%/12 -> 0.0055191667 | F40: =E40+(C40-E40)*$J$35 -> 0.13518205
A41: 44570 | B41: ='Nifty 50 Historical Data'!B43 -> 17094.35 | C41: =LN(B41/B42) -> -0.038161323 | D41: ='Monthly Vs Risk'!D41 -> -0.11448237 | E41: =Reference!$B$4%/12 -> 0.0055191667 | F41: =E41+(C41-E41)*$J$35 -> -0.11554708 | I41: Observation | J41: Predicted Y | K41: Residuals
A42: 44569 | B42: ='Nifty 50 Historical Data'!B44 -> 17759.3 | C42: =LN(B42/B43) -> 0.034430215 | D42: ='Monthly Vs Risk'!D42 -> 0.18027023 | E42: =Reference!$B$4%/12 -> 0.0055191667 | F42: =E42+(C42-E42)*$J$35 -> 0.085649955 | I42: 1 | J42: -0.031598858 | K42: -0.036523098
A43: 44568 | B43: ='Nifty 50 Historical Data'!B45 -> 17158.25 | C43: =LN(B43/B44) -> 0.083719949 | D43: ='Monthly Vs Risk'!D43 -> 0.26763202 | E43: =Reference!$B$4%/12 -> 0.0055191667 | F43: =E43+(C43-E43)*$J$35 -> 0.22226296 | I43: 2 | J43: 0.02750532 | K43: -0.067809584
A44: 44567 | B44: ='Nifty 50 Historical Data'!B46 -> 15780.25 | C44: =LN(B44/B45) -> -0.049712381 | D44: ='Monthly Vs Risk'!D44 -> -0.0020873348 | E44: =Reference!$B$4%/12 -> 0.0055191667 | F44: =E44+(C44-E44)*$J$35 -> -0.14756236 | I44: 3 | J44: 0.098546487 | K44: -0.088521739
A45: 44566 | B45: ='Nifty 50 Historical Data'!B47 -> 16584.55 | C45: =LN(B45/B46) -> -0.030756036 | D45: ='Monthly Vs Risk'!D45 -> -0.02188235 | E45: =Reference!$B$4%/12 -> 0.0055191667 | F45: =E45+(C45-E45)*$J$35 -> -0.095022349 | I45: 4 | J45: -0.0030015681 | K45: 0.059247895
A46: 44565 | B46: ='Nifty 50 Historical Data'!B48 -> 17102.55 | C46: =LN(B46/B47) -> -0.020956989 | D46: ='Monthly Vs Risk'!D46 -> 0.13110089 | E46: =Reference!$B$4%/12 -> 0.0055191667 | F46: =E46+(C46-E46)*$J$35 -> -0.067862995 | I46: 5 | J46: -0.062309824 | K46: 0.040555285
A47: 44564 | B47: ='Nifty 50 Historical Data'!B49 -> 17464.75 | C47: =LN(B47/B48) -> 0.039168839 | D47: ='Monthly Vs Risk'!D47 -> 0.30258464 | E47: =Reference!$B$4%/12 -> 0.0055191667 | F47: =E47+(C47-E47)*$J$35 -> 0.098783677 | I47: 6 | J47: -0.10636917 | K47: -0.0057142639
A48: 44563 | B48: ='Nifty 50 Historical Data'!B50 -> 16793.9 | C48: =LN(B48/B49) -> -0.031991596 | D48: ='Monthly Vs Risk'!D48 -> -0.1367329 | E48: =Reference!$B$4%/12 -> 0.0055191667 | F48: =E48+(C48-E48)*$J$35 -> -0.098446865 | I48: 7 | J48: 0.060686272 | K48: -0.072455441
A49: 44562 | B49: ='Nifty 50 Historical Data'!B51 -> 17339.85 | C49: =LN(B49/B50) -> -0.00081858775 | D49: ='Monthly Vs Risk'!D49 -> 0.056152823 | E49: =Reference!$B$4%/12 -> 0.0055191667 | F49: =E49+(C49-E49)*$J$35 -> -0.012046757 | I49: 8 | J49: 0.023208037 | K49: 0.10712138
A50: 44208 | B50: ='Nifty 50 Historical Data'!B52 -> 17354.05 | C50: =LN(B50/B51) -> 0.021601288 | D50: ='Monthly Vs Risk'!D50 -> 0.07346038 | E50: =Reference!$B$4%/12 -> 0.0055191667 | F50: =E50+(C50-E50)*$J$35 -> 0.050092891 | I50: 9 | J50: 0.070570458 | K50: -0.074561151
A51: 44207 | B51: ='Nifty 50 Historical Data'!B53 -> 16983.2 | C51: =LN(B51/B52) -> -0.03973704 | D51: ='Monthly Vs Risk'!D51 -> 0.10564878 | E51: =Reference!$B$4%/12 -> 0.0055191667 | F51: =E51+(C51-E51)*$J$35 -> -0.11991439 | I51: 10 | J51: 0.14559736 | K51: -0.067178233
A52: 44206 | B52: ='Nifty 50 Historical Data'!B54 -> 17671.65 | C52: =LN(B52/B53) -> 0.0030320399 | D52: ='Monthly Vs Risk'!D52 -> 0.011388372 | E52: =Reference!$B$4%/12 -> 0.0055191667 | F52: =E52+(C52-E52)*$J$35 -> -0.0013742336 | I52: 11 | J52: -0.19196533 | K52: 0.048499605
A53: 44205 | B53: ='Nifty 50 Historical Data'!B55 -> 17618.15 | C53: =LN(B53/B54) -> 0.027969887 | D53: ='Monthly Vs Risk'!D53 -> -0.020413485 | E53: =Reference!$B$4%/12 -> 0.0055191667 | F53: =E53+(C53-E53)*$J$35 -> 0.067744303 | I53: 12 | J53: -0.039864377 | K53: -0.12853445
... A60: 44198 | B60: ='Nifty 50 Historical Data'!B62 -> 14529.15 | C60: =LN(B60/B61) -> 0.063546297 | D60: ='Monthly Vs Risk'!D60 -> 0.29578457 | E60: =Reference!$B$4%/12 -> 0.0055191667 | F60: =E60+(C60-E60)*$J$35 -> 0.16634902 | I60: 19 | J60: 0.1524924 | K60: -0.30085468
A61: 44197 | B61: ='Nifty 50 Historical Data'!B63 -> 13634.6 | I61: 20 | J61: -0.032935984 | K61: 0.1450223
I62: 21 | J62: 0.010462 | K62: -0.0077136356
C63: =AVERAGE(C2:C60) -> 0.011024713 | F63: =AVERAGE(F2:F60) -> 0.020778517 | G63: Er (Monthly) | I63: 22 | J63: 0.019219373 | K63: -0.1208332
C64: CAPM Summary | I64: 23 | J64: 0.0087773534 | K64: 0.0042748436
C65: Monthly Rm (avg) | E65: =AVERAGE(C2:C60) -> 0.011024713 | I65: 24 | J65: -0.024556416 | K65: 0.048953966
C66: Annual Rm | E66: =E65*12 -> 0.13229656 | I66: 25 | J66: 0.18789705 | K66: 0.14416164
C67: Monthly Rf | E67: =AVERAGE(E2:E60) -> 0.0055191667 | I67: 26 | J67: 0.12514037 | K67: 0.10284701
C68: Annual Rf | E68: =E67*12 -> 0.06623 | I68: 27 | J68: -0.10382429 | K68: 0.020637637
C69: Beta | E69: =J35 -> 2.7716321 | I69: 28 | J69: 0.030974965 | K69: -0.067086331
C70: ke (annual CAPM) | E70: =E68+E69*(E66-E68) -> 0.2493422 | F70: 𝑬𝒙𝒑𝒆𝒄𝒕𝒆𝒅𝒓𝒆𝒕𝒖𝒓𝒏𝒐𝒏𝒆𝒒𝒖𝒊𝒕𝒚=𝒌𝒆= 𝒓𝒇+ β 𝒓𝒎 𝒓𝒇 | I70: 29 | J70: -0.094886874 | K70: 0.051940683
I71: 30 | J71: 0.056564825 | K71: -0.042758947
I72: 31 | J72: 0.072377721 | K72: -0.086861386
I73: 32 | J73: 0.047268844 | K73: -0.39994574
I74: 33 | J74: 0.086542749 | K74: -0.0012614762
I75: 34 | J75: -0.014906045 | K75: 0.26085153
I76: 35 | J76: -0.080617677 | K76: -1.0530139
I77: 36 | J77: -0.092512548 | K77: -0.46805147
I78: 37 | J78: -0.12204011 | K78: 0.13844869
I79: 38 | J79: 0.088670321 | K79: -0.080405582
I80: 39 | J80: 0.12113064 | K80: -0.045331336
I81: 40 | J81: -0.12959849 | K81: 0.015116116
I82: 41 | J82: 0.071598548 | K82: 0.10867168
... I100: 59 | J100: 0.15229761 | K100: 0.14348696

Sheet Monthly Vs Risk
A1: Date | B1: ATGL (Monthly) | C1: Simple Return (Ri) =[ Pt-P(t-1)/P(t-1)] | D1: Ri=Lognormal formula: LN(Pt/P(t-1) | E1: Add 10 | F1: Probability (Pi) | G1: Er = Sum of ( Ri*Pi) | H1: Variance= (Ri-Er)^2)*Pi
A2: 45669 | B2: ='Adani Total Gas Stock Price His'!B4 -> 566.7 | C2: =(B2-B3)/B3 -> -0.065853458 | D2: =LN(B2/B3) -> -0.068121955 | E2: =10+D2 -> 9.931878 | F2: =1/59 -> 0.016949153 | G2: =D2*F2 -> -0.0011546094 | H2: =(D2-$G$66)^2*F2 -> 9.4955636e-05
A3: 45668 | B3: ='Adani Total Gas Stock Price His'!B5 -> 606.65 | C3: =(B3-B4)/B4 -> -0.03950285 | D3: =LN(B3/B4) -> -0.040304264 | E3: =10+D3 -> 9.9596957 | F3: =1/59 -> 0.016949153 | G3: =D3*F3 -> -0.00068312312 | H3: =(D3-$G$66)^2*F3 -> 3.7490679e-05
A4: 45667 | B4: ='Adani Total Gas Stock Price His'!B6 -> 631.6 | C4: =(B4-B5)/B5 -> 0.010075164 | D4: =LN(B4/B5) -> 0.010024748 | E4: =10+D4 -> 10.010025 | F4: =1/59 -> 0.016949153 | G4: =D4*F4 -> 0.00016991098 | H4: =(D4-$G$66)^2*F4 -> 1.8431217e-07
A5: 45666 | B5: ='Adani Total Gas Stock Price His'!B7 -> 625.3 | C5: =(B5-B6)/B6 -> 0.05785823 | D5: =LN(B5/B6) -> 0.056246327 | E5: =10+D5 -> 10.056246 | F5: =1/59 -> 0.016949153 | G5: =D5*F5 -> 0.00095332757 | H5: =(D5-$G$66)^2*F5 -> 4.1561913e-05
A6: 45665 | B6: ='Adani Total Gas Stock Price His'!B8 -> 591.1 | C6: =(B6-B7)/B7 -> -0.021519616 | D6: =LN(B6/B7) -> -0.021754539 | E6: =10+D6 -> 9.9782455 | F6: =1/59 -> 0.016949153 | G6: =D6*F6 -> -0.00036872101 | H6: =(D6-$G$66)^2*F6 -> 1.3749226e-05
A7: 45664 | B7: ='Adani Total Gas Stock Price His'!B9 -> 604.1 | C7: =(B7-B8)/B8 -> -0.10603034 | D7: =LN(B7/B8) -> -0.11208344 | E7: =10+D7 -> 9.8879166 | F7: =1/59 -> 0.016949153 | G7: =D7*F7 -> -0.0018997193 | H7: =(D7-$G$66)^2*F7 -> 0.00023925333
A8: 45663 | B8: ='Adani Total Gas Stock Price His'!B10 -> 675.75 | C8: =(B8-B9)/B9 -> -0.011700183 | D8: =LN(B8/B9) -> -0.011769169 | E8: =10+D8 -> 9.9882308 | F8: =1/59 -> 0.016949153 | G8: =D8*F8 -> -0.00019947743 | H8: =(D8-$G$66)^2*F8 -> 5.7985136e-06
A9: 45662 | B9: ='Adani Total Gas Stock Price His'!B11 -> 683.75 | C9: =(B9-B10)/B10 -> 0.1392036 | D9: =LN(B9/B10) -> 0.13032942 | E9: =10+D9 -> 10.130329 | F9: =1/59 -> 0.016949153 | G9: =D9*F9 -> 0.0022089732 | H9: =(D9-$G$66)^2*F9 -> 0.00025894121
A10: 45661 | B10: ='Adani Total Gas Stock Price His'!B12 -> 600.2 | C10: =(B10-B11)/B11 -> -0.0039827415 | D10: =LN(B10/B11) -> -0.0039906937 | E10: =10+D10 -> 9.9960093 | F10: =1/59 -> 0.016949153 | G10: =D10*F10 -> -6.7638876e-05 | H10: =(D10-$G$66)^2*F10 -> 1.9469713e-06
A11: 45660 | B11: ='Adani Total Gas Stock Price His'!B13 -> 602.6 | C11: =(B11-B12)/B12 -> 0.081575877 | D11: =LN(B11/B12) -> 0.078419123 | E11: =10+D11 -> 10.078419 | F11: =1/59 -> 0.016949153 | G11: =D11*F11 -> 0.0013291377 | H11: =(D11-$G$66)^2*F11 -> 8.7114319e-05
A12: 45659 | B12: ='Adani Total Gas Stock Price His'!B14 -> 557.15 | C12: =(B12-B13)/B13 -> -0.13364951 | D12: =LN(B12/B13) -> -0.14346573 | E12: =10+D12 -> 9.8565343 | F12: =1/59 -> 0.016949153 | G12: =D12*F12 -> -0.0024316225 | H12: =(D12-$G$66)^2*F12 -> 0.0003823371
A13: 45658 | B13: ='Adani Total Gas Stock Price His'!B15 -> 643.1 | C13: =(B13-B14)/B14 -> -0.15498325 | D13: =LN(B13/B14) -> -0.16839883 | E13: =10+D13 -> 9.8316012 | F13: =1/59 -> 0.016949153 | G13: =D13*F13 -> -0.0028542174 | H13: =(D13-$G$66)^2*F13 -> 0.00051981514
... A60: 44198 | B60: ='Adani Total Gas Stock Price His'!B62 -> 512.2 | C60: =(B60-B61)/B61 -> 0.34418055 | D60: =LN(B60/B61) -> 0.29578457 | E60: =10+D60 -> 10.295785 | F60: =1/59 -> 0.016949153 | G60: =D60*F60 -> 0.0050132979 | H60: =(D60-$G$66)^2*F60 -> 0.0014161732
A61: 44197 | B61: ='Adani Total Gas Stock Price His'!B63 -> 381.05
A63: Count | B63: =COUNT(B2:B61) -> 60 | C63: =COUNT(C2:C61) -> 59 | D63: =COUNT(D2:D61) -> 59
A64: 1 | B64: ARM (Monthly) | C64: =AVEDEV(C2:C60) -> 0.14819556 | D64: =AVEDEV(D2:D60) -> 0.14363625
A65: 2 | B65: GM (Monthly) | C65: =GEOMEAN(E2:E60) -> 10.003866 | D65: =C65-10 -> 0.0038656469
A66: 3 | B66: Expected Return | C66: sum of (Ri*Pi) | G66: =SUM(G2:G60) -> 0.0067271095
A67: 4 | B67: Variance = sum of[(Ri-ER)^2*Pi] | H67: =SUM(H2:H60) -> 0.055664734
A68: 5 | B68: Risk (volatility of not achieving expected return) | C68: sqtr of Variance | H68: =SQRT(H67) -> 0.23593375 | I68: =H68*SQRT(12) -> 0.81729848
A69: 6 | B69: Coefficient of Cor | C69: =_xlfn.COVARIANCE.S(#REF!,#REF!) -> #REF!
A72: Stock Price Prediction based on return
A73: 46030 | B73: =B2*(1+D65) -> 568.89066 | C73: =B2*(1+D64) -> 648.09866
A75: Stock price prediction based on risk and return
A76: 46030 | B76: =(B2*(1+G66)) -> 570.51225
B77: =B76*H68 -> 134.60309
B78: =B76-B77 -> 435.90916
A79: Price Rang | B79: between 570.512 to 435.909

Sheet Dividend 
B2: Ex-Dividend Date | C2: Dividend | D2: Type | E2: Payment Date | F2: Yield
B3: Jun 13, 2025 | C3: 0.25 | D3: 12M | E3: Jul 25, 2025 | F3: 0.0004
B4: Jun 14, 2024 | C4: 0.25 | D4: 12M | E4: Jul 25, 2024 | F4: 0.0003
B5: Jul 07, 2023 | C5: 0.25 | D5: 12M | E5: Aug 17, 2023 | F5: 0.0004
B6: Jul 14, 2022 | C6: 0.25 | D6: 12M | E6: Aug 25, 2022 | F6: 0.0001
B7: Jun 24, 2021 | C7: 0.25 | D7: 12M | E7: Aug 11, 2021 | F7: 0.0002
B8: Mar 26, 2020 | C8: 0.25 | D8: I | E8: Apr 18, 2020 | F8: 0.0059
B9: Jul 26, 2019 | C9: 0.25 | D9: 12M | E9: Sep 05, 2019 | F9: 0.0016
B11: GM | C11: =GEOMEAN(Table2[Dividend]) -> 0.25

Sheet Adani Total Gas Stock Price His
A1: Data Source | C1: https://www.investing.com/equities/adani-gas
A2: Data Downloaded | C2: 46027
A3: Date | B3: Price | C3: Open | D3: High | E3: Low | F3: Vol. | G3: Change % | I3: Volume (Million) | J3: Volume (Million)
A4: 45669 | B4: 566.7 | C4: 609.05 | D4: 610.9 | E4: 561 | F4: 8.51M | G4: -0.0659 | I4: =_xlfn.TEXTBEFORE(F4,"M") -> 8.51 | J4: =I4*1000000 -> 8510000
A5: 45668 | B5: 606.65 | C5: 631.6 | D5: 634.9 | E5: 599.05 | F5: 9.69M | G5: -0.0395 | I5: =_xlfn.TEXTBEFORE(F5,"M") -> 9.69 | J5: =I5*1000000 -> 9690000
A6: 45667 | B6: 631.6 | C6: 630.05 | D6: 675 | E6: 613.55 | F6: 25.15M | G6: 0.0101 | I6: =_xlfn.TEXTBEFORE(F6,"M") -> 25.15 | J6: =I6*1000000 -> 25150000
A7: 45666 | B7: 625.3 | C7: 593.9 | D7: 798 | E7: 588.2 | F7: 97.48M | G7: 0.0579 | I7: =_xlfn.TEXTBEFORE(F7,"M") -> 97.48 | J7: =I7*1000000 -> 97480000
A8: 45665 | B8: 591.1 | C8: 617 | D8: 644.5 | E8: 577.1 | F8: 13.65M | G8: -0.0215 | I8: =_xlfn.TEXTBEFORE(F8,"M") -> 13.65 | J8: =I8*1000000 -> 13650000
A9: 45664 | B9: 604.1 | C9: 677 | D9: 684 | E9: 602.45 | F9: 12.98M | G9: -0.106 | I9: =_xlfn.TEXTBEFORE(F9,"M") -> 12.98 | J9: =I9*1000000 -> 12980000
A10: 45663 | B10: 675.75 | C10: 685 | D10: 721 | E10: 608.15 | F10: 38.14M | G10: -0.0117 | I10: =_xlfn.TEXTBEFORE(F10,"M") -> 38.14 | J10: =I10*1000000 -> 38140000
A11: 45662 | B11: 683.75 | C11: 599 | D11: 693 | E11: 587.1 | F11: 40.22M | G11: 0.1392 | I11: =_xlfn.TEXTBEFORE(F11,"M") -> 40.22 | J11: =I11*1000000 -> 40220000
A12: 45661 | B12: 600.2 | C12: 599.05 | D12: 634 | E12: 545.5 | F12: 15.13M | G12: -0.004 | I12: =_xlfn.TEXTBEFORE(F12,"M") -> 15.13 | J12: =I12*1000000 -> 15130000
A13: 45660 | B13: 602.6 | C13: 559.4 | D13: 641.9 | E13: 532.6 | F13: 25.54M | G13: 0.0816 | I13: =_xlfn.TEXTBEFORE(F13,"M") -> 25.54 | J13: =I13*1000000 -> 25540000
A14: 45659 | B14: 557.15 | C14: 647.5 | D14: 654.4 | E14: 555 | F14: 13.70M | G14: -0.1336 | I14: =_xlfn.TEXTBEFORE(F14,"M") -> 13.70 | J14: =I14*1000000 -> 13700000
A15: 45658 | B15: 643.1 | C15: 751 | D15: 766.6 | E15: 607.4 | F15: 35.32M | G15: -0.155 | I15: =_xlfn.TEXTBEFORE(F15,"M") -> 35.32 | J15: =I15*1000000 -> 35320000
... A63: 44197 | B63: 381.05 | C63: 377.4 | D63: 389.4 | E63: 341 | F63: 23.51M | G63: 0.0145 | I63: =_xlfn.TEXTBEFORE(F63,"M") -> 23.51 | J63: =I63*1000000 -> 23510000

Sheet Nifty 50 Historical Data
A1: Data Source | C1: https://www.investing.com/equities/adani-gas
A2: Data Downloaded | C2: 46027
A3: Date | B3: Price | C3: Open | D3: High | E3: Low | F3: Vol. | G3: Change %
A4: 45669 | B4: 26129.6 | C4: 26325.8 | D4: 26325.8 | E4: 25693.25 | F4: 5.37B | G4: -0.0028
A5: 45668 | B5: 26202.95 | C5: 25696.85 | D5: 26310.45 | E5: 25318.45 | F5: 5.50B | G5: 0.0187
A6: 45667 | B6: 25722.1 | C6: 24620.55 | D6: 26104.2 | E6: 24605.95 | F6: 6.24B | G6: 0.0451
A7: 45666 | B7: 24611.1 | C7: 24432.7 | D7: 25448.95 | E7: 24432.7 | F7: 5.98B | G7: 0.0075
A8: 45665 | B8: 24426.85 | C8: 24734.9 | D8: 25153.65 | E8: 24337.5 | F8: 5.87B | G8: -0.0138
A9: 45664 | B9: 24768.35 | C9: 25551.35 | D9: 25608.1 | E9: 24598.6 | F9: 6.28B | G9: -0.0293
A10: 45663 | B10: 25517.05 | C10: 24669.7 | D10: 25669.35 | E10: 24473 | F10: 7.06B | G10: 0.031
A11: 45662 | B11: 24750.7 | C11: 24311.9 | D11: 25116.25 | E11: 23935.75 | F11: 8.55B | G11: 0.0171
A12: 45661 | B12: 24334.2 | C12: 23341.1 | D12: 24457.65 | E12: 21743.65 | F12: 7.66B | G12: 0.0346
A13: 45660 | B13: 23519.35 | C13: 22194.55 | D13: 23869.6 | E13: 21964.6 | F13: 6.24B | G13: 0.063
A14: 45659 | B14: 22124.7 | C14: 23528.6 | D14: 23807.3 | E14: 22104.85 | F14: 5.65B | G14: -0.0589
A15: 45658 | B15: 23508.4 | C15: 23637.65 | D15: 24226.7 | E15: 22786.9 | F15: 6.46B | G15: -0.0058
... A63: 44197 | B63: 13634.6 | C63: 13996.1 | D63: 14753.55 | E63: 13596.75 | F63: 13.02B | G63: -0.0248

Sheet Reference
A1: References used to perform the task in tis file
A3: 46030 | B3: https://tradingeconomics.com/india/government-bond-yield
A4: India 10Y Bond Yield | B4: 6.623
